CHANGES.rst
MANIFEST.in
README.rst
requirements.txt
setup.py
django_visitor_information/__init__.py
django_visitor_information/constants.py
django_visitor_information/middleware.py
django_visitor_information/settings.py
django_visitor_information/static/GeoLiteCity.dat
django_visitor_information_middleware.egg-info/PKG-INFO
django_visitor_information_middleware.egg-info/SOURCES.txt
django_visitor_information_middleware.egg-info/dependency_links.txt
django_visitor_information_middleware.egg-info/requires.txt
django_visitor_information_middleware.egg-info/top_level.txt