Metadata-Version: 1.1
Name: django-visitor-information-middleware
Version: 0.1.0
Summary: A collection of Django middleware classes which make writing timezone and location aware applications easier
Home-page: https://github.com/Kami/django-visitor-information-middleware/
Author: Tomaz Muraus
Author-email: tomaz+pypi@tomaz.me
License: Apache License (2.0)
Platform: UNKNOWN
Classifier: Development Status :: 4 - Beta
Classifier: Environment :: Console
Classifier: Intended Audience :: Developers
Classifier: Operating System :: OS Independent
Classifier: License :: OSI Approved :: Apache Software License
Classifier: Programming Language :: Python
Classifier: Programming Language :: Python :: 2.6
Classifier: Programming Language :: Python :: 2.7
Classifier: Programming Language :: Python :: Implementation :: PyPy
Classifier: Topic :: Software Development :: Libraries :: Python Modules
